{
  "circle": null,
  "dilate": 100,
  "layers": {
    "beach": {
      "tags": {
        "natural": "beach"
      }
    },
    "building": {
      "tags": {
        "building": true,
        "landuse": "construction"
      }
    },
    "forest": {
      "tags": {
        "landuse": "forest"
      }
    },
    "green": {
      "tags": {
        "landuse": [
          "grass",
          "orchard"
        ],
        "leisure": "park",
        "natural": [
          "island",
          "wood"
        ]
      }
    },
    "parking": {
      "tags": {
        "amenity": "parking",
        "highway": "pedestrian",
        "man_made": "pier"
      }
    },
    "perimeter": {},
    "streets": {},
    "water": {
      "tags": {
        "natural": [
          "water",
          "bay"
        ]
      }
    }
  },
  "radius": 800,
  "style": {
    "background": {
      "fc": "#F2F4CB",
      "zorder": -1
    },
    "beach": {
      "ec": "#2F3737",
      "fc": "#FCE19C",
      "hatch": "ooo...",
      "hatch_c": "#d4d196",
      "lw": 1,
      "zorder": 3
    },
    "building": {
      "ec": "#2F3737",
      "lw": 0.5,
      "palette": [
        "#433633",
        "#FF5E5B"
      ],
      "zorder": 5
    },
    "forest": {
      "ec": "#2F3737",
      "fc": "#64B96A",
      "lw": 1,
      "zorder": 2
    },
    "green": {
      "ec": "#2F3737",
      "fc": "#8BB174",
      "hatch": "ooo...",
      "hatch_c": "#A7C497",
      "lw": 1,
      "zorder": 1
    },
    "parking": {
      "ec": "#2F3737",
      "fc": "#F2F4CB",
      "lw": 1,
      "zorder": 3
    },
    "perimeter": {
      "fill": false,
      "lw": 0,
      "zorder": 0
    },
    "streets": {
      "alpha": 1,
      "ec": "#475657",
      "fc": "#2F3737",
      "lw": 0,
      "width": {
        "cycleway": 3.5,
        "footway": 1,
        "motorway": 5,
        "pedestrian": 2,
        "primary": 4.5,
        "residential": 3,
        "secondary": 4,
        "service": 2,
        "tertiary": 3.5,
        "trunk": 5,
        "unclassified": 2
      },
      "zorder": 4
    },
    "water": {
      "ec": "#2F3737",
      "fc": "#a8e1e6",
      "hatch": "ooo...",
      "hatch_c": "#9bc3d4",
      "lw": 1,
      "zorder": 3
    }
  }
}
