{
  "circle": null,
  "layers": {
    "building": {
      "tags": {
        "building": true
      }
    },
    "perimeter": {},
    "streets": {
      "width": {
        "motorway": 5,
        "primary": 4,
        "residential": 2,
        "secondary": 3,
        "tertiary": 2,
        "trunk": 5
      }
    }
  },
  "radius": 400,
  "style": {
    "background": {
      "fc": "#fff",
      "zorder": -1
    },
    "building": {
      "ec": "#000",
      "fc": "#fff",
      "lw": 0.5,
      "zorder": 5
    },
    "perimeter": {
      "fill": false,
      "lw": 0,
      "zorder": 0
    },
    "streets": {
      "fc": "#000",
      "lw": 0,
      "zorder": 4
    }
  }
}
